{
    "ultima_actualizacion": "01:41:36",
    "tablas": {
        "pts": [
            {
                "Rank": 107,
                "Nombre": "Nikola Vucevic",
                "Antes": 16952,
                "Hoy": 0,
                "Total": 16952,
                "Diff": "8",
                "Antece": "Bob Cousy",
                "Nota": "",
                "game_status": "not_started"
            },
            {
                "Rank": 140,
                "Nombre": "CJ McCollum",
                "Antes": 15640,
                "Hoy": 0,
                "Total": 15640,
                "Diff": "7",
                "Antece": "Antoine Walker",
                "Nota": "",
                "game_status": "not_started"
            },
            {
                "Rank": 183,
                "Nombre": "Andrew Wiggins",
                "Antes": 14420,
                "Hoy": 0,
                "Total": 14420,
                "Diff": "5",
                "Antece": "Jeff Green",
                "Nota": "",
                "game_status": "not_started"
            },
            {
                "Rank": 210,
                "Nombre": "Jayson Tatum",
                "Antes": 13784,
                "Hoy": 0,
                "Total": 13784,
                "Diff": "6",
                "Antece": "Bill Laimbeer",
                "Nota": "",
                "game_status": "playing"
            },
            {
                "Rank": 211,
                "Nombre": "Donovan Mitchell",
                "Antes": 13743,
                "Hoy": 5,
                "Total": 13748,
                "Diff": "36",
                "Antece": "Jayson Tatum",
                "Nota": "",
                "game_status": "playing"
            },
            {
                "Rank": 231,
                "Nombre": "Khris Middleton",
                "Antes": 13013,
                "Hoy": 0,
                "Total": 13013,
                "Diff": "4",
                "Antece": "Jeff Mullins",
                "Nota": "",
                "game_status": "not_started"
            }
        ],
        "trb": [
            {
                "Rank": 41,
                "Nombre": "Nikola Vucevic",
                "Antes": 10308,
                "Hoy": 0,
                "Total": 10308,
                "Diff": "62",
                "Antece": "Otis Thorpe",
                "Nota": "",
                "game_status": "not_started"
            },
            {
                "Rank": 248,
                "Nombre": "Jarrett Allen",
                "Antes": 5345,
                "Hoy": 0,
                "Total": 5345,
                "Diff": "2",
                "Antece": "Mark West",
                "Nota": "",
                "game_status": "playing"
            }
        ],
        "ast": [
            {
                "Rank": 170,
                "Nombre": "T.J. McConnell",
                "Antes": 3559,
                "Hoy": 2,
                "Total": 3561,
                "Diff": "2",
                "Antece": "Pete Maravich",
                "Nota": "",
                "game_status": "playing"
            },
            {
                "Rank": 225,
                "Nombre": "Khris Middleton",
                "Antes": 3092,
                "Hoy": 0,
                "Total": 3092,
                "Diff": "2",
                "Antece": "Clifford Robinson",
                "Nota": "",
                "game_status": "not_started"
            },
            {
                "Rank": 233,
                "Nombre": "CJ McCollum",
                "Antes": 3052,
                "Hoy": 0,
                "Total": 3052,
                "Diff": "3",
                "Antece": "Blake Griffin",
                "Nota": "",
                "game_status": "not_started"
            },
            {
                "Rank": 249,
                "Nombre": "Tyrese Haliburton",
                "Antes": 2947,
                "Hoy": 0,
                "Total": 2947,
                "Diff": "15",
                "Antece": "Tom Gola",
                "Nota": "",
                "game_status": "playing"
            }
        ],
        "stl": [
            {
                "Rank": 236,
                "Nombre": "Khris Middleton",
                "Antes": 912,
                "Hoy": 0,
                "Total": 912,
                "Diff": "",
                "Antece": "John Long",
                "Nota": "Mismo total",
                "game_status": "not_started"
            }
        ],
        "blk": [
            {
                "Rank": 141,
                "Nombre": "Nikola Vucevic",
                "Antes": 851,
                "Hoy": 0,
                "Total": 851,
                "Diff": "13",
                "Antece": "Kenyon Martin",
                "Nota": "",
                "game_status": "not_started"
            },
            {
                "Rank": 165,
                "Nombre": "Jakob Poeltl",
                "Antes": 763,
                "Hoy": 0,
                "Total": 763,
                "Diff": "4",
                "Antece": "Duane Causwell",
                "Nota": "",
                "game_status": "not_started"
            },
            {
                "Rank": 184,
                "Nombre": "Jarrett Allen",
                "Antes": 715,
                "Hoy": 0,
                "Total": 715,
                "Diff": "2",
                "Antece": "Clemon Johnson",
                "Nota": "",
                "game_status": "playing"
            },
            {
                "Rank": 251,
                "Nombre": "Nic Claxton",
                "Antes": 553,
                "Hoy": 0,
                "Total": 553,
                "Diff": "",
                "Antece": "Nate Thurmond",
                "Nota": "Mismo total",
                "game_status": "playing"
            }
        ],
        "fg3": [
            {
                "Rank": 18,
                "Nombre": "CJ McCollum",
                "Antes": 2025,
                "Hoy": 0,
                "Total": 2025,
                "Diff": "61",
                "Antece": "Eric Gordon",
                "Nota": "",
                "game_status": "not_started"
            },
            {
                "Rank": 39,
                "Nombre": "Donovan Mitchell",
                "Antes": 1673,
                "Hoy": 1,
                "Total": 1674,
                "Diff": "6",
                "Antece": "Kevin Love",
                "Nota": "",
                "game_status": "playing"
            },
            {
                "Rank": 51,
                "Nombre": "Jayson Tatum",
                "Antes": 1546,
                "Hoy": 0,
                "Total": 1546,
                "Diff": "",
                "Antece": "Eddie Jones",
                "Nota": "Mismo total",
                "game_status": "playing"
            },
            {
                "Rank": 65,
                "Nombre": "Khris Middleton",
                "Antes": 1419,
                "Hoy": 0,
                "Total": 1419,
                "Diff": "2",
                "Antece": "Jordan Clarkson",
                "Nota": "",
                "game_status": "not_started"
            },
            {
                "Rank": 73,
                "Nombre": "Terry Rozier",
                "Antes": 1356,
                "Hoy": 0,
                "Total": 1356,
                "Diff": "3",
                "Antece": "Evan Fournier",
                "Nota": "",
                "game_status": "not_started"
            },
            {
                "Rank": 113,
                "Nombre": "Andrew Wiggins",
                "Antes": 1174,
                "Hoy": 0,
                "Total": 1174,
                "Diff": "4",
                "Antece": "Jamal Murray",
                "Nota": "",
                "game_status": "not_started"
            },
            {
                "Rank": 114,
                "Nombre": "Jaylen Brown",
                "Antes": 1174,
                "Hoy": 0,
                "Total": 1174,
                "Diff": "",
                "Antece": "Andrew Wiggins",
                "Nota": "Mismo total",
                "game_status": "playing"
            },
            {
                "Rank": 133,
                "Nombre": "Norman Powell",
                "Antes": 1098,
                "Hoy": 0,
                "Total": 1098,
                "Diff": "2",
                "Antece": "1100",
                "Nota": "",
                "game_status": "not_started"
            },
            {
                "Rank": 155,
                "Nombre": "Kevin Huerter",
                "Antes": 1044,
                "Hoy": 0,
                "Total": 1044,
                "Diff": "",
                "Antece": "Isaiah Thomas",
                "Nota": "Mismo total",
                "game_status": "not_started"
            },
            {
                "Rank": 165,
                "Nombre": "Anfernee Simons",
                "Antes": 1007,
                "Hoy": 0,
                "Total": 1007,
                "Diff": "2",
                "Antece": "Morris Peterson",
                "Nota": "",
                "game_status": "playing"
            },
            {
                "Rank": 171,
                "Nombre": "Coby White",
                "Antes": 993,
                "Hoy": 0,
                "Total": 993,
                "Diff": "3",
                "Antece": "Rafer Alston",
                "Nota": "",
                "game_status": "not_started"
            },
            {
                "Rank": 178,
                "Nombre": "Derrick White",
                "Antes": 984,
                "Hoy": 0,
                "Total": 984,
                "Diff": "2",
                "Antece": "Doug McDermott",
                "Nota": "",
                "game_status": "playing"
            },
            {
                "Rank": 179,
                "Nombre": "Tyler Herro",
                "Antes": 984,
                "Hoy": 0,
                "Total": 984,
                "Diff": "",
                "Antece": "Derrick White",
                "Nota": "Mismo total",
                "game_status": "not_started"
            },
            {
                "Rank": 203,
                "Nombre": "Nikola Vucevic",
                "Antes": 928,
                "Hoy": 0,
                "Total": 928,
                "Diff": "6",
                "Antece": "Chucky Atkins",
                "Nota": "",
                "game_status": "not_started"
            },
            {
                "Rank": 216,
                "Nombre": "Darius Garland",
                "Antes": 904,
                "Hoy": 1,
                "Total": 905,
                "Diff": "1",
                "Antece": "Grayson Allen",
                "Nota": "A tiro de 1",
                "game_status": "playing"
            },
            {
                "Rank": 221,
                "Nombre": "Michael Porter Jr.",
                "Antes": 884,
                "Hoy": 0,
                "Total": 884,
                "Diff": "1",
                "Antece": "Davis Bertans",
                "Nota": "A tiro de 1",
                "game_status": "playing"
            },
            {
                "Rank": 236,
                "Nombre": "Tyrese Haliburton",
                "Antes": 856,
                "Hoy": 0,
                "Total": 856,
                "Diff": "3",
                "Antece": "Avery Bradley",
                "Nota": "",
                "game_status": "playing"
            }
        ],
        "g": [
            {
                "Rank": 167,
                "Nombre": "Nikola Vucevic",
                "Antes": 986,
                "Hoy": 0,
                "Total": 986,
                "Diff": "",
                "Antece": "Mike Dunleavy",
                "Nota": "Mismo total",
                "game_status": "not_started"
            }
        ]
    },
    "notificaciones": [],
    "cache_buster": 1763772096
}